printer/__init__.py
printer/printer.py
autograder_vives-0.0.2.dist-info/LICENSE
autograder_vives-0.0.2.dist-info/METADATA
autograder_vives-0.0.2.dist-info/WHEEL
autograder_vives-0.0.2.dist-info/top_level.txt
autograder_vives-0.0.2.dist-info/RECORD
